[
  {
    "name": "Bancolombia",
    "code": "BANCOL",
    "icon": "🏛️",
    "logo": "https://bancolombia.com/logo.png",
    "countryCode": "CO",
    "website": "https://www.bancolombia.com",
    "phone": "+57-1-343-0000",
    "bankingType": "commercial",
    "supportsInternational": true,
    "isActive": true,
    "isPopular": true,
    "displayOrder": 1
  },
  {
    "name": "Banco de Bogotá",
    "code": "BBOGOT",
    "icon": "🏦",
    "logo": "https://bancodebogota.com/logo.png",
    "countryCode": "CO",
    "website": "https://www.bancodebogota.com",
    "phone": "+57-1-332-0000",
    "bankingType": "commercial",
    "supportsInternational": true,
    "isActive": true,
    "isPopular": true,
    "displayOrder": 2
  },
  {
    "name": "Banco Davivienda",
    "code": "DAVIVI",
    "icon": "💳",
    "logo": "https://davivienda.com/logo.png",
    "countryCode": "CO",
    "website": "https://www.davivienda.com",
    "phone": "+57-1-330-0000",
    "bankingType": "commercial",
    "supportsInternational": true,
    "isActive": true,
    "isPopular": true,
    "displayOrder": 3
  },
  {
    "name": "BBVA Colombia",
    "code": "BBVACO",
    "icon": "💰",
    "logo": "https://bbva.com.co/logo.png",
    "countryCode": "CO",
    "website": "https://www.bbva.com.co",
    "phone": "+57-1-224-2000",
    "bankingType": "commercial",
    "supportsInternational": true,
    "isActive": true,
    "isPopular": true,
    "displayOrder": 4
  },
  {
    "name": "Banco Popular",
    "code": "BPOPUL",
    "icon": "🌟",
    "logo": "https://bancopopular.com.co/logo.png",
    "countryCode": "CO",
    "website": "https://www.bancopopular.com.co",
    "phone": "+57-1-289-0000",
    "bankingType": "commercial",
    "supportsInternational": false,
    "isActive": true,
    "isPopular": true,
    "displayOrder": 5
  },
  {
    "name": "Banco Caja Social",
    "code": "BCAJSO",
    "icon": "🤝",
    "logo": "https://cajasocial.com/logo.png",
    "countryCode": "CO",
    "website": "https://www.cajasocial.com",
    "phone": "+57-1-320-1000",
    "bankingType": "commercial",
    "supportsInternational": false,
    "isActive": true,
    "isPopular": false,
    "displayOrder": 6
  },
  {
    "name": "Scotiabank Colpatria",
    "code": "SCOTIA",
    "icon": "🍁",
    "logo": "https://scotiabankcolpatria.com/logo.png",
    "countryCode": "CO",
    "website": "https://www.scotiabankcolpatria.com",
    "phone": "+57-1-756-7878",
    "bankingType": "commercial",
    "supportsInternational": true,
    "isActive": true,
    "isPopular": false,
    "displayOrder": 7
  },
  {
    "name": "Banco Santander Colombia",
    "code": "SANTCO",
    "icon": "🔴",
    "logo": "https://santander.com.co/logo.png",
    "countryCode": "CO",
    "website": "https://www.santander.com.co",
    "phone": "+57-1-313-1313",
    "bankingType": "commercial",
    "supportsInternational": true,
    "isActive": true,
    "isPopular": false,
    "displayOrder": 8
  },
  {
    "name": "Banco Itaú Colombia",
    "code": "ITAUCO",
    "icon": "🧡",
    "logo": "https://itau.com.co/logo.png",
    "countryCode": "CO",
    "website": "https://www.itau.com.co",
    "phone": "+57-1-756-8000",
    "bankingType": "commercial",
    "supportsInternational": true,
    "isActive": true,
    "isPopular": false,
    "displayOrder": 9
  },
  {
    "name": "Nequi",
    "code": "NEQUI",
    "icon": "📱",
    "logo": "https://nequi.com.co/logo.png",
    "countryCode": "CO",
    "website": "https://www.nequi.com.co",
    "phone": "+57-1-343-0000",
    "bankingType": "digital",
    "supportsInternational": false,
    "isActive": true,
    "isPopular": true,
    "displayOrder": 10
  },
  {
    "name": "Bank of America",
    "code": "BOA",
    "icon": "🇺🇸",
    "logo": "https://bankofamerica.com/logo.png",
    "countryCode": "US",
    "website": "https://www.bankofamerica.com",
    "phone": "+1-800-432-1000",
    "bankingType": "commercial",
    "supportsInternational": true,
    "isActive": true,
    "isPopular": true,
    "displayOrder": 1
  },
  {
    "name": "JPMorgan Chase",
    "code": "JPMC",
    "icon": "🏢",
    "logo": "https://chase.com/logo.png",
    "countryCode": "US",
    "website": "https://www.chase.com",
    "phone": "+1-800-935-9935",
    "bankingType": "commercial",
    "supportsInternational": true,
    "isActive": true,
    "isPopular": true,
    "displayOrder": 2
  },
  {
    "name": "Wells Fargo",
    "code": "WELLS",
    "icon": "🐎",
    "logo": "https://wellsfargo.com/logo.png",
    "countryCode": "US",
    "website": "https://www.wellsfargo.com",
    "phone": "+1-800-869-3557",
    "bankingType": "commercial",
    "supportsInternational": true,
    "isActive": true,
    "isPopular": true,
    "displayOrder": 3
  },
  {
    "name": "Citibank",
    "code": "CITI",
    "icon": "🌐",
    "logo": "https://citibank.com/logo.png",
    "countryCode": "US",
    "website": "https://www.citibank.com",
    "phone": "+1-800-374-9700",
    "bankingType": "commercial",
    "supportsInternational": true,
    "isActive": true,
    "isPopular": true,
    "displayOrder": 4
  },
  {
    "name": "Goldman Sachs",
    "code": "GOLD",
    "icon": "💎",
    "logo": "https://goldmansachs.com/logo.png",
    "countryCode": "US",
    "website": "https://www.goldmansachs.com",
    "phone": "+1-877-255-8100",
    "bankingType": "investment",
    "supportsInternational": true,
    "isActive": true,
    "isPopular": false,
    "displayOrder": 5
  },
  {
    "name": "Banco Santander España",
    "code": "SANTES",
    "icon": "🇪🇸",
    "logo": "https://santander.es/logo.png",
    "countryCode": "ES",
    "website": "https://www.santander.es",
    "phone": "+34-91-289-0000",
    "bankingType": "commercial",
    "supportsInternational": true,
    "isActive": true,
    "isPopular": true,
    "displayOrder": 1
  },
  {
    "name": "BBVA España",
    "code": "BBVAES",
    "icon": "🔵",
    "logo": "https://bbva.es/logo.png",
    "countryCode": "ES",
    "website": "https://www.bbva.es",
    "phone": "+34-90-224-4365",
    "bankingType": "commercial",
    "supportsInternational": true,
    "isActive": true,
    "isPopular": true,
    "displayOrder": 2
  },
  {
    "name": "CaixaBank",
    "code": "CAIXA",
    "icon": "⭐",
    "logo": "https://caixabank.es/logo.png",
    "countryCode": "ES",
    "website": "https://www.caixabank.es",
    "phone": "+34-90-240-3650",
    "bankingType": "commercial",
    "supportsInternational": true,
    "isActive": true,
    "isPopular": true,
    "displayOrder": 3
  },
  {
    "name": "Banco Sabadell",
    "code": "SABADE",
    "icon": "🔷",
    "logo": "https://sabadell.com/logo.png",
    "countryCode": "ES",
    "website": "https://www.sabadell.com",
    "phone": "+34-90-232-3232",
    "bankingType": "commercial",
    "supportsInternational": true,
    "isActive": true,
    "isPopular": true,
    "displayOrder": 4
  },
  {
    "name": "Bankinter",
    "code": "BANKIN",
    "icon": "🚀",
    "logo": "https://bankinter.es/logo.png",
    "countryCode": "ES",
    "website": "https://www.bankinter.es",
    "phone": "+34-91-339-6200",
    "bankingType": "commercial",
    "supportsInternational": true,
    "isActive": true,
    "isPopular": false,
    "displayOrder": 5
  },
  {
    "name": "ING España",
    "code": "INGES",
    "icon": "🧡",
    "logo": "https://ing.es/logo.png",
    "countryCode": "ES",
    "website": "https://www.ing.es",
    "phone": "+34-90-202-0202",
    "bankingType": "digital",
    "supportsInternational": true,
    "isActive": true,
    "isPopular": false,
    "displayOrder": 6
  }
]
